{
  "type": "minecraft:crafting_shaped",
  "pattern": [
    "XX#",
    "  X",
    "  X"
  ],
  "key": {
    "X": [
      {
        "tag": "minecraft:planks"
      }
    ],
    "#": [
      {
        "item": "minecraft:diamond"
      },
      {
        "tag": "c:diamonds"
      },
      {
        "tag": "forge:gems/diamond"
      }
    ]
  },
  "result": {
    "item": "weaponmod:boomerang.diamond"
  },
  "conditions": [
    {
      "type": "weaponmod:config_conditional",
      "weapon": "boomerang"
    }
  ],
  "fabric:load_conditions": [
    {
      "condition": "weaponmod:config_conditional",
      "weapon": "boomerang"
    }
  ]
}
