{
  "type": "minecraft:crafting_shaped",
  "category": "equipment",
  "pattern": [
    " XX",
    " #X",
    "#  "
  ],
  "key": {
    "X": {
      "item": "minecraft:cobblestone"
    },
    "#": {
      "item": "minecraft:stick"
    }
  },
  "result": {
    "id": "weaponmod:halberd.stone"
  },
  "neoforge:conditions": [
    {
      "type": "weaponmod:config_conditional",
      "weapon": "halberd"
    }
  ],
  "fabric:load_conditions": [
    {
      "condition": "weaponmod:config_conditional",
      "weapon": "halberd"
    }
  ]
}
